pyheart/__init__.py
pyheart/cli.py
pyheart/core/__init__.py
pyheart/core/client.py
pyheart/core/integration.py
pyheart/core/security.py
pyheart/core/server.py
pyheart/core/workflow.py
brainsait_pyheart-0.1.0.dist-info/METADATA
brainsait_pyheart-0.1.0.dist-info/WHEEL
brainsait_pyheart-0.1.0.dist-info/entry_points.txt
brainsait_pyheart-0.1.0.dist-info/top_level.txt
brainsait_pyheart-0.1.0.dist-info/RECORD
