Metadata-Version: 2.4
Name: brainsait-pyheart
Version: 0.1.0
Summary: Healthcare Interoperability & Workflow Engine - Universal integration platform for healthcare systems
Author-email: "Dr. Fadil" <fadil@brainsait.com>, BrainSAIT Team <team@brainsait.com>
Maintainer-email: BrainSAIT Healthcare Innovation Lab <healthcare@brainsait.com>
License: Apache-2.0
Project-URL: Homepage, https://github.com/brainsait/pyheart
Project-URL: Documentation, https://pyheart.readthedocs.io
Project-URL: Repository, https://github.com/brainsait/pyheart
Project-URL: Issues, https://github.com/brainsait/pyheart/issues
Project-URL: Changelog, https://github.com/brainsait/pyheart/blob/main/CHANGELOG.md
Keywords: healthcare,fhir,hl7,interoperability,integration,workflow,orchestration,api-gateway,health-informatics,medical-integration,healthcare-api
Classifier: Development Status :: 4 - Beta
Classifier: Intended Audience :: Healthcare Industry
Classifier: Topic :: Scientific/Engineering :: Medical Science Apps.
Classifier: Topic :: System :: Networking
Classifier: License :: OSI Approved :: Apache Software License
Classifier: Programming Language :: Python :: 3
Classifier: Programming Language :: Python :: 3.8
Classifier: Programming Language :: Python :: 3.9
Classifier: Programming Language :: Python :: 3.10
Classifier: Programming Language :: Python :: 3.11
Classifier: Programming Language :: Python :: 3.12
Classifier: Operating System :: OS Independent
Classifier: Framework :: FastAPI
Requires-Python: >=3.8
Requires-Dist: fhir.resources>=6.5.0
Requires-Dist: fastapi>=0.100.0
Requires-Dist: uvicorn[standard]>=0.22.0
Requires-Dist: httpx>=0.24.0
Requires-Dist: pydantic>=2.0
Requires-Dist: pydantic-settings>=2.0
Requires-Dist: sqlalchemy>=2.0
Requires-Dist: alembic>=1.11.0
Requires-Dist: asyncpg>=0.28.0
Requires-Dist: redis>=4.5.0
Requires-Dist: aiokafka>=0.8.0
Requires-Dist: motor>=3.2.0
Requires-Dist: cryptography>=41.0.0
Requires-Dist: python-jose[cryptography]>=3.3.0
Requires-Dist: passlib[bcrypt]>=1.7.4
Requires-Dist: python-multipart>=0.0.6
Requires-Dist: aiofiles>=23.1.0
Requires-Dist: orjson>=3.9.0
Requires-Dist: python-dateutil>=2.8.2
Requires-Dist: pytz>=2023.3
Requires-Dist: tenacity>=8.2.0
Requires-Dist: structlog>=23.1.0
Requires-Dist: prometheus-client>=0.17.0
Requires-Dist: opentelemetry-api>=1.18.0
Requires-Dist: opentelemetry-sdk>=1.18.0
Requires-Dist: opentelemetry-instrumentation-fastapi>=0.39b0
Requires-Dist: grpcio>=1.56.0
Requires-Dist: grpcio-tools>=1.56.0
Requires-Dist: hl7>=0.8.0
Requires-Dist: pydicom>=2.4.0
Requires-Dist: lxml>=4.9.0
Requires-Dist: jsonschema>=4.18.0
Requires-Dist: pyyaml>=6.0
Requires-Dist: click>=8.1.0
Requires-Dist: rich>=13.4.0
Requires-Dist: python-consul>=1.1.0
Requires-Dist: aiocache[redis]>=0.12.0
Provides-Extra: dev
Requires-Dist: pytest>=7.3.0; extra == "dev"
Requires-Dist: pytest-asyncio>=0.21.0; extra == "dev"
Requires-Dist: pytest-cov>=4.1.0; extra == "dev"
Requires-Dist: pytest-timeout>=2.1.0; extra == "dev"
Requires-Dist: black>=23.3.0; extra == "dev"
Requires-Dist: flake8>=6.0.0; extra == "dev"
Requires-Dist: mypy>=1.3.0; extra == "dev"
Requires-Dist: isort>=5.12.0; extra == "dev"
Requires-Dist: pre-commit>=3.3.0; extra == "dev"
Requires-Dist: pytest-mock>=3.11.0; extra == "dev"
Requires-Dist: factory-boy>=3.2.1; extra == "dev"
Requires-Dist: faker>=18.11.0; extra == "dev"
Requires-Dist: responses>=0.23.0; extra == "dev"
Requires-Dist: testcontainers[kafka,postgres,redis]>=3.7.0; extra == "dev"
Provides-Extra: docs
Requires-Dist: sphinx>=7.0.0; extra == "docs"
Requires-Dist: sphinx-rtd-theme>=1.2.0; extra == "docs"
Requires-Dist: sphinx-autodoc-typehints>=1.23.0; extra == "docs"
Requires-Dist: myst-parser>=2.0.0; extra == "docs"
Requires-Dist: sphinxcontrib-openapi>=0.8.0; extra == "docs"
Provides-Extra: cloud
Requires-Dist: boto3>=1.26.0; extra == "cloud"
Requires-Dist: azure-servicebus>=7.11.0; extra == "cloud"
Requires-Dist: google-cloud-pubsub>=2.18.0; extra == "cloud"
Requires-Dist: kubernetes>=27.2.0; extra == "cloud"
Provides-Extra: legacy
Requires-Dist: python-hl7>=0.4.0; extra == "legacy"
Requires-Dist: pymllp>=1.2.0; extra == "legacy"
Requires-Dist: pynetdicom>=2.0.0; extra == "legacy"
